Modules/Phylogenetic.py
Modules/Prediction.py
Modules/__init__.py
plasmidperxx-0.1.data/scripts/plasmidperm
plasmidperxx-0.1.data/scripts/plasmidpermm
plasmidperxx-0.1.data/scripts/plasmidpermmm
plasmidperxx-0.1.data/scripts/plasmidperx
plasmidperxx-0.1.data/scripts/plasmidperxx
plasmidperxx-0.1.dist-info/LICENSE
plasmidperxx-0.1.dist-info/METADATA
plasmidperxx-0.1.dist-info/WHEEL
plasmidperxx-0.1.dist-info/top_level.txt
plasmidperxx-0.1.dist-info/RECORD
